install_locked_env-0.3.1.dist-info/METADATA
install_locked_env-0.3.1.dist-info/WHEEL
install_locked_env-0.3.1.dist-info/entry_points.txt
install_locked_env-0.3.1.dist-info/licenses/LICENSE.txt
install_locked_env/__init__.py
install_locked_env/__main__.py
install_locked_env/_version.py
install_locked_env/downloaders.py
install_locked_env/environments.py
install_locked_env/parsers.py
install_locked_env-0.3.1.dist-info/RECORD
