Metadata-Version: 2.4
Name: install-locked-env
Version: 0.3.1
Summary: Helper to install (web) locked environments
Author-Email: "pierre.augier" <pierre.augier@univ-grenoble-alpes.fr>
License-Expression: BSD-3-Clause
License-File: LICENSE.txt
Classifier: Development Status :: 5 - Production/Stable
Classifier: Programming Language :: Python
Classifier: Programming Language :: Python :: 3
Classifier: Programming Language :: Python :: 3.11
Classifier: Programming Language :: Python :: 3.12
Classifier: Programming Language :: Python :: 3.13
Classifier: Programming Language :: Python :: 3.14
Project-URL: Repository, https://foss.heptapod.net/fluiddyn/install-locked-env
Requires-Python: >=3.11
Requires-Dist: typer>=0.9.0
Requires-Dist: httpx>=0.27.0
Requires-Dist: rich>=13.0.0
Requires-Dist: requests>=2.32.5
